djeasyroute/__init__.py
djeasyroute-0.0.3.dist-info/LICENSE
djeasyroute-0.0.3.dist-info/METADATA
djeasyroute-0.0.3.dist-info/WHEEL
djeasyroute-0.0.3.dist-info/top_level.txt
djeasyroute-0.0.3.dist-info/RECORD
