Metadata-Version: 2.1
Name: djeasyroute
Version: 0.0.3
Summary: A simple class based route system for django similar to flask
Home-page: https://github.com/Goggin/djeasyroute
Author: Ryan Goggin
Author-email: info@ryangoggin.net
License: UNKNOWN
Platform: UNKNOWN
Classifier: Development Status :: 3 - Alpha
Classifier: Framework :: Django
Classifier: License :: OSI Approved :: MIT License
Classifier: Operating System :: OS Independent
Classifier: Intended Audience :: Developers
Classifier: Topic :: Software Development
Requires-Dist: django
